pyfrx/__init__.py
pyfrx/main.py
pyfrx/supported_currencies.py
pyfrx-0.0.4.dist-info/METADATA
pyfrx-0.0.4.dist-info/WHEEL
pyfrx-0.0.4.dist-info/top_level.txt
pyfrx-0.0.4.dist-info/RECORD
